mycelium_ei/__init__.py
mycelium_ei/__main__.py
mycelium_ei/interpreter.py
mycelium_ei_lang-0.1.2.dist-info/licenses/LICENSE
mycelium_ei_lang-0.1.2.dist-info/METADATA
mycelium_ei_lang-0.1.2.dist-info/WHEEL
mycelium_ei_lang-0.1.2.dist-info/entry_points.txt
mycelium_ei_lang-0.1.2.dist-info/top_level.txt
mycelium_ei_lang-0.1.2.dist-info/RECORD
