Metadata-Version: 2.4
Name: mycelium-ei-lang
Version: 0.1.2
Summary: Revolutionary bio-inspired programming language with quantum computing integration
Home-page: https://github.com/MichaelCrowe11/mycelium-ei-lang
Author: Michael Benjamin Crowe
Author-email: Michael Benjamin Crowe <michael.benjamin.crowe@gmail.com>
License: Proprietary - See LICENSE file
Project-URL: Homepage, https://github.com/MichaelCrowe11/mycelium-ei-lang
Project-URL: Documentation, https://mycelium-ei-lang.readthedocs.io
Project-URL: Repository, https://github.com/MichaelCrowe11/mycelium-ei-lang
Project-URL: Issues, https://github.com/MichaelCrowe11/mycelium-ei-lang/issues
Classifier: Development Status :: 3 - Alpha
Classifier: Intended Audience :: Developers
Classifier: Intended Audience :: Science/Research
Classifier: Topic :: Scientific/Engineering :: Bio-Informatics
Classifier: Topic :: Scientific/Engineering :: Artificial Intelligence
Classifier: Topic :: Software Development :: Compilers
Classifier: License :: Other/Proprietary License
Classifier: Programming Language :: Python :: 3
Classifier: Programming Language :: Python :: 3.8
Classifier: Programming Language :: Python :: 3.9
Classifier: Programming Language :: Python :: 3.10
Classifier: Programming Language :: Python :: 3.11
Requires-Python: >=3.8
License-File: LICENSE
Dynamic: author
Dynamic: home-page
Dynamic: license-file
Dynamic: requires-python
